fakenamegeneratorAPI/UI.py
fakenamegeneratorAPI/__init__.py
fakenamegeneratorAPI/parser_.py
fakenamegeneratorAPI-0.0.9.dist-info/LICENSE.txt
fakenamegeneratorAPI-0.0.9.dist-info/METADATA
fakenamegeneratorAPI-0.0.9.dist-info/WHEEL
fakenamegeneratorAPI-0.0.9.dist-info/top_level.txt
fakenamegeneratorAPI-0.0.9.dist-info/RECORD
