Metadata-Version: 2.1
Name: fakenamegeneratorAPI
Version: 0.0.9
Summary: my version of fakenamegenerator API
Home-page: https://github.com/catarium/fakenamegenerator_API
Author: Catarium
License: Apache-2.0 License
Platform: UNKNOWN
Classifier: Programming Language :: Python :: 3.6
Classifier: Topic :: Internet
Requires-Python: >=3.7
Requires-Dist: requests (~=2.24.0)
Requires-Dist: beautifulsoup4 (~=4.9.1)
